[
    {
        "url": "https://www.iaps.ai/news/fellowship",
        "timestamp": "2025-04-25T18:44:00.037573",
        "publisher": "IAPS",
        "category": "NEWS"
    },
    {
        "url": "https://www.iaps.ai/renan-araujo",
        "timestamp": "2025-04-25T18:44:00.037573",
        "publisher": "IAPS",
        "category": "NEWS"
    },
    {
        "url": "https://www.iaps.ai/oliver-guest",
        "timestamp": "2025-04-25T18:44:00.037573",
        "publisher": "IAPS",
        "category": "NEWS"
    },
    {
        "url": "https://www.iaps.ai/amin-oueslati",
        "timestamp": "2025-04-25T18:44:00.037573",
        "publisher": "IAPS",
        "category": "NEWS"
    },
    {
        "url": "https://www.iaps.ai/ourresearch2",
        "timestamp": "2025-04-25T18:44:00.037573",
        "publisher": "IAPS",
        "category": "NEWS"
    },
    {
        "url": "https://www.iaps.ai/research/tag/International+governance+%26+China",
        "timestamp": "2025-04-25T18:44:00.037573",
        "publisher": "IAPS",
        "category": "NEWS"
    },
    {
        "url": "https://www.iaps.ai/fellowship",
        "timestamp": "2025-04-25T18:44:00.037573",
        "publisher": "IAPS",
        "category": "NEWS"
    },
    {
        "url": "https://www.iaps.ai/research/adapting-cybersecurity-frameworks",
        "timestamp": "2025-04-25T18:44:00.037573",
        "publisher": "IAPS",
        "category": "NEWS"
    },
    {
        "url": "https://www.iaps.ai/research/governance-gap",
        "timestamp": "2025-04-25T18:44:00.037573",
        "publisher": "IAPS",
        "category": "NEWS"
    },
    {
        "url": "https://www.iaps.ai/ulysse-richard",
        "timestamp": "2025-04-25T18:44:00.037573",
        "publisher": "IAPS",
        "category": "NEWS"
    },
    {
        "url": "https://www.iaps.ai/research-tmp",
        "timestamp": "2025-04-25T18:44:00.037573",
        "publisher": "IAPS",
        "category": "NEWS"
    },
    {
        "url": "https://www.iaps.ai/research/tag/Linkpost",
        "timestamp": "2025-04-25T18:44:00.037573",
        "publisher": "IAPS",
        "category": "NEWS"
    },
    {
        "url": "https://www.iaps.ai/research/category/Link+Post",
        "timestamp": "2025-04-25T18:44:00.037573",
        "publisher": "IAPS",
        "category": "NEWS"
    },
    {
        "url": "https://www.iaps.ai/research/tag/Compute+governance",
        "timestamp": "2025-04-25T18:44:00.037573",
        "publisher": "IAPS",
        "category": "NEWS"
    },
    {
        "url": "https://www.iaps.ai/research/ai-safety-needs-southeast-asias-expertise-and-engagement",
        "timestamp": "2025-04-25T18:44:00.037573",
        "publisher": "IAPS",
        "category": "NEWS"
    },
    {
        "url": "https://www.iaps.ai/ourresearch",
        "timestamp": "2025-04-25T18:44:00.037573",
        "publisher": "IAPS",
        "category": "NEWS"
    },
    {
        "url": "https://www.iaps.ai/research/expert-in-ai-hardware",
        "timestamp": "2025-04-25T18:44:00.037573",
        "publisher": "IAPS",
        "category": "NEWS"
    },
    {
        "url": "https://www.iaps.ai/",
        "timestamp": "2025-04-25T18:44:00.037573",
        "publisher": "IAPS",
        "category": "NEWS"
    },
    {
        "url": "https://www.iaps.ai/research/understanding-aisis",
        "timestamp": "2025-04-25T18:44:00.037573",
        "publisher": "IAPS",
        "category": "NEWS"
    },
    {
        "url": "https://www.iaps.ai/research/future-of-ai-summit-series",
        "timestamp": "2025-04-25T18:44:00.037573",
        "publisher": "IAPS",
        "category": "NEWS"
    },
    {
        "url": "https://www.iaps.ai/governance-history-independence-funding",
        "timestamp": "2025-04-25T18:44:00.037573",
        "publisher": "IAPS",
        "category": "NEWS"
    },
    {
        "url": "https://www.iaps.ai/research/ai-chip-smuggling-into-china",
        "timestamp": "2025-04-25T18:44:00.037573",
        "publisher": "IAPS",
        "category": "NEWS"
    },
    {
        "url": "https://www.iaps.ai/sumaya-nur-adan",
        "timestamp": "2025-04-25T18:44:00.037573",
        "publisher": "IAPS",
        "category": "NEWS"
    },
    {
        "url": "https://www.iaps.ai/research/dialogue-topics",
        "timestamp": "2025-04-25T18:44:00.037573",
        "publisher": "IAPS",
        "category": "NEWS"
    },
    {
        "url": "https://www.iaps.ai/research/who-should-develop-ai-evaluations",
        "timestamp": "2025-04-25T18:44:00.037573",
        "publisher": "IAPS",
        "category": "NEWS"
    },
    {
        "url": "https://www.iaps.ai/research",
        "timestamp": "2025-04-25T18:44:00.037573",
        "publisher": "IAPS",
        "category": "NEWS"
    },
    {
        "url": "https://www.iaps.ai/research/china-aisi-counterparts",
        "timestamp": "2025-04-25T18:44:00.037573",
        "publisher": "IAPS",
        "category": "NEWS"
    },
    {
        "url": "https://www.iaps.ai/research/international-network-aisis",
        "timestamp": "2025-04-25T18:44:00.037573",
        "publisher": "IAPS",
        "category": "NEWS"
    },
    {
        "url": "https://www.iaps.ai/careers",
        "timestamp": "2025-04-25T18:44:00.037573",
        "publisher": "IAPS",
        "category": "NEWS"
    },
    {
        "url": "https://www.iaps.ai/research/secure-governable-chips",
        "timestamp": "2025-04-25T18:44:00.037573",
        "publisher": "IAPS",
        "category": "NEWS"
    }
]